skewnorm/__init__.py
skewnorm/normalization.py
tests/__init__.py
tests/test_normalization.py
skewnormlib-0.1.3.dist-info/LICENSE
skewnormlib-0.1.3.dist-info/METADATA
skewnormlib-0.1.3.dist-info/WHEEL
skewnormlib-0.1.3.dist-info/top_level.txt
skewnormlib-0.1.3.dist-info/RECORD
