Metadata-Version: 2.1
Name: skewnormlib
Version: 0.1.3
Summary: A Python library for skew-weighted normalization
Home-page: https://github.com/mohdnihal03/skewnormlib
Author: Mohammed Nihal
Author-email: Mohd Nihal <mohdnihalll03@gmail.com>
License: MIT License
Keywords: skewness,normalization,data preprocessing,machine learning
Classifier: Development Status :: 3 - Alpha
Classifier: Intended Audience :: Developers
Classifier: Intended Audience :: Science/Research
Classifier: License :: OSI Approved :: MIT License
Classifier: Programming Language :: Python :: 3
Classifier: Programming Language :: Python :: 3.6
Classifier: Programming Language :: Python :: 3.7
Classifier: Programming Language :: Python :: 3.8
Classifier: Programming Language :: Python :: 3.9
Classifier: Topic :: Scientific/Engineering :: Artificial Intelligence
Requires-Python: >=3.6
License-File: LICENSE
Requires-Dist: numpy
Requires-Dist: scipy
Requires-Dist: scikit-learn
